layaberr/__init__.py
layaberr/_authorization.py
layaberr/_default.py
layaberr/_validation.py
layaberr/version.py
layaberr-2.2.0.dist-info/LICENSE
layaberr-2.2.0.dist-info/METADATA
layaberr-2.2.0.dist-info/WHEEL
layaberr-2.2.0.dist-info/top_level.txt
layaberr-2.2.0.dist-info/RECORD
