Metadata-Version: 2.1
Name: layaberr
Version: 2.2.0
Summary: Thin wrapper for layabase and layab error handling
Home-page: https://colin-b.github.io/layaberr/
Author: Colin Bounouar
Author-email: colin.bounouar.dev@gmail.com
Maintainer: Colin Bounouar
Maintainer-email: colin.bounouar.dev@gmail.com
License: MIT
Download-URL: https://pypi.org/project/layaberr/
Project-URL: GitHub, https://github.com/Colin-b/layaberr
Project-URL: Changelog, https://github.com/Colin-b/layaberr/blob/master/CHANGELOG.md
Project-URL: Issues, https://github.com/Colin-b/layaberr/issues
Keywords: error,rest,flask
Platform: Windows
Platform: Linux
Classifier: Development Status :: 5 - Production/Stable
Classifier: Intended Audience :: Developers
Classifier: License :: OSI Approved :: MIT License
Classifier: Natural Language :: English
Classifier: Programming Language :: Python
Classifier: Programming Language :: Python :: 3
Classifier: Programming Language :: Python :: 3.6
Classifier: Programming Language :: Python :: 3.7
Classifier: Programming Language :: Python :: 3.8
Classifier: Topic :: Software Development :: Build Tools
Requires-Python: >=3.6
Requires-Dist: flask-restplus (==0.13.*)
Provides-Extra: testing
Requires-Dist: pytest-flask (==0.15.*) ; extra == 'testing'
Requires-Dist: pytest-cov (==2.*) ; extra == 'testing'
